hybridtfidf/__init__.py
hybridtfidf/utils.py
hybridtfidf-1.1.0.dist-info/LICENSE.txt
hybridtfidf-1.1.0.dist-info/METADATA
hybridtfidf-1.1.0.dist-info/WHEEL
hybridtfidf-1.1.0.dist-info/top_level.txt
hybridtfidf-1.1.0.dist-info/RECORD
