Metadata-Version: 2.1
Name: hybridtfidf
Version: 1.1.0
Summary: An implementation of the Hybrid TF-IDF microblog summarisation algorithm as proposed by David Ionuye and Jugal K. Kalitaß.
Home-page: https://github.com/jamalrahman/hybridtfidf
Author: Jamal Rahman
Author-email: jamalrahman95@gmail.com
License: MIT
Keywords: TFIDF,Text Summarization,NLP
Platform: UNKNOWN
Classifier: Development Status :: 5 - Production/Stable
Classifier: Intended Audience :: Developers
Classifier: License :: OSI Approved :: MIT License
Classifier: Programming Language :: Python :: 3
License-File: LICENSE.txt
